SBMLDiagrams/__init__.py
SBMLDiagrams/_version.py
SBMLDiagrams/drawNetwork.py
SBMLDiagrams/editSBML.py
SBMLDiagrams/exportSBML.py
SBMLDiagrams/point.py
SBMLDiagrams/processSBML.py
SBMLDiagrams/styleSBML.py
SBMLDiagrams/visualizeInfo.py
SBMLDiagrams/visualizeSBML.py
SBMLDiagrams-1.4.2.dist-info/LICENSE
SBMLDiagrams-1.4.2.dist-info/METADATA
SBMLDiagrams-1.4.2.dist-info/WHEEL
SBMLDiagrams-1.4.2.dist-info/top_level.txt
SBMLDiagrams-1.4.2.dist-info/RECORD
