Metadata-Version: 2.1
Name: SBMLDiagrams
Version: 1.4.2
Summary: Visualize, edit and write SBML files.
Home-page: https://github.com/sys-bio/SBMLDiagrams
Author: Jin Xu, Jessie Jiang, Herbert M. Sauro
Author-email: jin.xu.phys@gmail.com
License: MIT License
Platform: UNKNOWN
Classifier: License :: OSI Approved :: MIT License
Classifier: Programming Language :: Python :: 3.8
Classifier: Programming Language :: Python :: 3.9
Classifier: Programming Language :: Python :: 3.10
Classifier: Programming Language :: Python :: 3.11
Classifier: Operating System :: OS Independent
Requires-Python: >=3.8
Requires-Dist: coverage
Requires-Dist: pip (>20)
Requires-Dist: numpy
Requires-Dist: pandas
Requires-Dist: python-libsbml
Requires-Dist: simplesbml
Requires-Dist: skia-python
Requires-Dist: Ipython
Requires-Dist: Pillow
Requires-Dist: setuptools
Requires-Dist: openpyxl
Requires-Dist: opencv-python
Requires-Dist: networkx
Requires-Dist: matplotlib
